code/__init__.py
code/client.py
code/factory.py
code/xybase.py
code/xymodel.py
code/xyview.py
code/test/__init__.py
code/test/calculator.py
code/test/image_diff.py
code/test/signal_test.py
code/test/test_calculator.py
code/test/xyfigure_test.py
code/test/differentiation/__init__.py
code/test/differentiation/test.py
code/test/img_same_diff/__init__.py
code/test/img_same_diff/test_image_diff.py
process/__init__.py
process/exodus/__init__.py
process/exodus/population.py
process/exodus/visualization.py
process/tpav/__init__.py
process/tpav/client.py
process/tpav/pendulum_rigid_reference.py
process/tpav/pendulum_tpav.py
process/tpav/test_three_points_angular_velocity.py
process/tpav/three_points_angular_velocity.py
process/tpav/three_points_angular_velocity_test.py
process/ui/__init__.py
process/ui/dash/__init__.py
process/ui/dash/app copy.py
process/ui/dash/app.py
process/ui/dash/assets/__init__.py
process/ui/data/__init__.py
xyfigure/__init__.py
xyfigure/client.py
xyfigure/factory.py
xyfigure/xybase.py
xyfigure/xymodel.py
xyfigure/xyview.py
xyfigure/test/__init__.py
xyfigure/test/image_diff.py
xyfigure/test/image_diff_test.py
xyfigure/test/signal_test.py
xyfigure/test/xyfigure_test.py
xyfigure-0.0.6.dist-info/METADATA
xyfigure-0.0.6.dist-info/WHEEL
xyfigure-0.0.6.dist-info/top_level.txt
xyfigure-0.0.6.dist-info/RECORD
