Metadata-Version: 2.1
Name: xyfigure
Version: 0.0.6
Summary: A library for xy plotting and processing
Home-page: https://github.com/sandialabs/sibl
Author: Chad B. Hovey
Author-email: chovey@sandia.gov
License: UNKNOWN
Platform: UNKNOWN
Classifier: Programming Language :: Python :: 3
Classifier: License :: OSI Approved :: MIT License
Classifier: Operating System :: OS Independent
Requires-Python: >=3.6
